Linear.py
abstract_classes.py
activations.py
cnn.py
dataset.py
evaluation.py
loss.py
model.py
optim.py
utils.py
visualize.py
pyray2-0.0.4.dist-info/METADATA
pyray2-0.0.4.dist-info/WHEEL
pyray2-0.0.4.dist-info/top_level.txt
pyray2-0.0.4.dist-info/RECORD
