Metadata-Version: 2.1
Name: pyray2
Version: 0.0.4
Summary: Mini Neural Network Library
Home-page: https://github.com/AmrElsersy/DL-Framework
Author: mamoanwar97
Author-email: 1601323@eng.asu.edu.eg
License: UNKNOWN
Platform: UNKNOWN
Requires-Dist: numpy
Requires-Dist: matplotlib
Requires-Dist: pandas
